{"type": "fallback", "job_by_role": {"driver": "Accountant", "engineer": "Accountant", "admin": "Senior Engineer", "high_manager": "Driver", "manager": "Accountant", "construction_worker": "Driver", "accountant": "Site Supervisor"}, "job_most_common": "Construction Worker", "year_median_by_job": {"Software Engineer": 2011, "Driver": 2009, "Project Manager": 2009, "HR Specialist": 2010, "Senior Engineer": 2009, "Operations Coordinator": 2008, "Accountant": 2011, "Site Supervisor": 2010, "Construction Worker": 2010}, "global_year_median": 2010}